airos/__init__.py
airos/airos6.py
airos/airos8.py
airos/base.py
airos/data.py
airos/discovery.py
airos/exceptions.py
airos/helpers.py
airos/model_map.py
airos/py.typed
airos-0.6.3.dist-info/licenses/LICENSE
airos-0.6.3.dist-info/METADATA
airos-0.6.3.dist-info/WHEEL
airos-0.6.3.dist-info/top_level.txt
airos-0.6.3.dist-info/RECORD
