Metadata-Version: 2.4
Name: airos
Version: 0.6.3
Summary: Ubiquiti airOS module(s) for Python 3.
Maintainer: CoMPaTech
License-Expression: MIT
Project-URL: Source Code, https://github.com/compatech/python-airos
Project-URL: Bug Reports, https://github.com/compatech/python-airos/issues
Keywords: home,automation,ubiquiti,uisp,airos,module
Classifier: Development Status :: 5 - Production/Stable
Classifier: Intended Audience :: Developers
Classifier: Operating System :: OS Independent
Classifier: Programming Language :: Python :: 3.14
Classifier: Programming Language :: Python :: 3.13
Classifier: Topic :: Home Automation
Requires-Python: >=3.13
License-File: LICENSE
Requires-Dist: aiohttp>=3.8.0
Requires-Dist: mashumaro>=3.14.0
Dynamic: license-file
